pattern_utils/__init__.py
pattern_utils/generator.py
pattern_utils-0.1.0.dist-info/METADATA
pattern_utils-0.1.0.dist-info/WHEEL
pattern_utils-0.1.0.dist-info/licenses/LICENSE
pattern_utils-0.1.0.dist-info/RECORD
