Metadata-Version: 2.3
Name: pattern_utils
Version: 0.1.0
Summary: Pattern matching utilities.
Project-URL: HomePage, https://github.com/Jamie-Chang/pattern-utils
Author-email: Jamie Chang <jamie.cheng.chang@gmail.com>
Maintainer-email: Jamie Chang <jamie.cheng.chang@gmail.com>
License:                                  Apache License
Classifier: Development Status :: 4 - Beta
Classifier: Programming Language :: Python
Classifier: Programming Language :: Python :: 3.10
Classifier: Programming Language :: Python :: 3.11
Classifier: Programming Language :: Python :: 3.12
Classifier: Programming Language :: Python :: 3.13
Requires-Python: >=3.10
